hdl/timer/counter_4bit_dec.v

module counter_4bit_dec (
        output wire [3:0] data_out,
        output wire tc,
        output wire zero,
        input wire loadn, clock, clear, enable,
        input wire [3:0] data_in
    );
    
    reg [ 3: 0 ] cur_state;
    assign data_out = cur_state; 

    assign zero = (cur_state == 0) ? 1 : 0;
    assign tc = ((cur_state == 0) & enable) ? 1 : 0;

    always @(posedge clock)
    begin: COUNTER
        if (enable) begin
            if (!loadn) begin
                cur_state <= data_in;
            end
            else begin
                if (cur_state == 4'b0000) begin
                    cur_state <= 4'b1001;
                    //tc <= 1;
                end
                else begin
                    cur_state <= cur_state - 1;
                    //tc <= 0;
                end
            end
        end
    end

    always @(negedge clear) begin
        if (!clear) begin
            cur_state <= 4'b0000;
            //tc <= 1;
        end
    end

endmodule

hdl/timer/counter_4bit_hex.v

module counter_4bit_hex (
        output wire [3:0] data_out,
        output wire tc,
        output wire zero,
        input wire loadn, clock, clear, enable,
        input wire [3:0] data_in
    );
    
    reg [ 3: 0 ] cur_state;
    assign data_out = cur_state; 

    assign zero = (cur_state == 0) ? 1 : 0;
    assign tc = ((cur_state == 0) & enable) ? 1 : 0;

    always @(posedge clock)
    begin: COUNTER
        if (enable) begin
            if (!loadn) begin
                cur_state <= data_in;
            end
            else begin
                if (cur_state == 4'b0000) begin
                    cur_state <= 4'b0101;
                    // tc <= 1;
                end
                else begin
                    cur_state <= cur_state - 1;
                    // tc <= 0;
                end
            end
        end
    end

    always @(negedge clear) begin
        if (!clear) begin
            cur_state <= 4'b0000;
            //// tc <= 1;
        end
    end

endmodule

hdl/timer/timer.v
module timer (
    input wire [3:0] data_in,
    input wire loadn, clock, clear, enable,
    output wire [3:0] sec_ones, sec_tens, mins,
    output wire tc, zero
);
    // wire [3:0] sec_out, ten_sec_out;
    wire en_tens_sec, en_min, en_sec;
    wire zero_sec, zero_ten_sec, zero_min;

    counter_4bit_dec seconds(.loadn(loadn), .clock(clock), .clear(clear), .enable(enable), .data_in(data_in), .data_out(sec_ones), .tc(en_tens_sec), .zero(zero_sec));

    counter_4bit_hex ten_secs(.loadn(loadn), .clock(clock), .clear(clear), .enable(en_tens_sec), .data_in(sec_ones), .data_out(sec_tens), .tc(en_min), .zero(zero_ten_sec));

    counter_4bit_dec minutes(.loadn(loadn), .clock(clock), .clear(clear), .enable(en_min), .data_in(sec_tens), .data_out(mins), .tc(en_sec), .zero(zero_sec));

    and(zero, zero_sec, zero_ten_sec, zero_min);
    
    assign zero = zero_sec & zero_ten_sec && zero_min;

endmodule

test/timer_tb.v
`timescale 1us/1ps
module encoder_tb ();

    reg [3:0] data_in;
    reg loadn, clear, clock, enable;

    integer i;

    timer DUT(.data_in(data_in), .loadn(loadn), .clock(clock),
    .clear(clear), .enable(enable));

    initial begin
        $dumpfile("test/timer_tb.vcd");
        $dumpvars;
        
        for(i = 0; i < 3005; i++) begin
            #5000 clock <= ~clock;
        end
    end


    initial begin
        loadn = 0;
        clear = 0;
        clock = 1;
        enable = 1;
        data_in = 4'd5;
        #16000;
        loadn = 1;
        #100000;
        clear = 1;
        #8000;
        clear = 0;
    end
    
endmodule

test/timer_tb.vcd
$date
	Fri Apr 30 02:48:38 2021
$end
$version
	Icarus Verilog
$end
$timescale
	1ps
$end
$scope module encoder_tb $end
$var reg 1 ! clear $end
$var reg 1 " clock $end
$var reg 4 # data_in [3:0] $end
$var reg 1 $ enable $end
$var reg 1 % loadn $end
$var integer 32 & i [31:0] $end
$scope module DUT $end
$var wire 1 ! clear $end
$var wire 1 " clock $end
$var wire 4 ' data_in [3:0] $end
$var wire 1 $ enable $end
$var wire 1 % loadn $end
$var wire 1 ( tc $end
$var wire 1 ) zero $end
$var wire 1 * zero_min $end
$var wire 1 + zero_sec $end
$var wire 1 , zero_ten_sec $end
$var wire 4 - sec_tens [3:0] $end
$var wire 4 . sec_ones [3:0] $end
$var wire 4 / mins [3:0] $end
$var wire 1 0 en_tens_sec $end
$var wire 1 1 en_sec $end
$var wire 1 2 en_min $end
$scope module minutes $end
$var wire 1 ! clear $end
$var wire 1 " clock $end
$var wire 4 3 data_out [3:0] $end
$var wire 1 % loadn $end
$var wire 1 + zero $end
$var wire 1 1 tc $end
$var wire 1 2 enable $end
$var wire 4 4 data_in [3:0] $end
$var reg 4 5 cur_state [3:0] $end
$scope begin COUNTER $end
$upscope $end
$upscope $end
$scope module seconds $end
$var wire 1 ! clear $end
$var wire 1 " clock $end
$var wire 4 6 data_in [3:0] $end
$var wire 4 7 data_out [3:0] $end
$var wire 1 $ enable $end
$var wire 1 % loadn $end
$var wire 1 + zero $end
$var wire 1 0 tc $end
$var reg 4 8 cur_state [3:0] $end
$scope begin COUNTER $end
$upscope $end
$upscope $end
$scope module ten_secs $end
$var wire 1 ! clear $end
$var wire 1 " clock $end
$var wire 4 9 data_in [3:0] $end
$var wire 4 : data_out [3:0] $end
$var wire 1 0 enable $end
$var wire 1 % loadn $end
$var wire 1 , zero $end
$var wire 1 2 tc $end
$var reg 4 ; cur_state [3:0] $end
$scope begin COUNTER $end
$upscope $end
$upscope $end
$upscope $end
$upscope $end
$enddefinitions $end
#0
$dumpvars
b0 ;
b0 :
b101 9
b101 8
b101 7
b101 6
b0 5
b0 4
b0 3
02
01
00
b0 /
b101 .
b0 -
1,
x+
z*
x)
z(
b101 '
b0 &
0%
1$
b101 #
1"
0!
$end
#5000000000
0"
b1 &
#10000000000
1"
b10 &
#15000000000
0"
b11 &
#16000000000
1%
#20000000000
b100 .
b100 7
b100 9
b100 8
1"
b100 &
#25000000000
0"
b101 &
#30000000000
b11 .
b11 7
b11 9
b11 8
1"
b110 &
#35000000000
0"
b111 &
#40000000000
b10 .
b10 7
b10 9
b10 8
1"
b1000 &
#45000000000
0"
b1001 &
#50000000000
b1 .
b1 7
b1 9
b1 8
1"
b1010 &
#55000000000
0"
b1011 &
#60000000000
11
12
10
1+
b0 .
b0 7
b0 9
b0 8
1"
b1100 &
#65000000000
0"
b1101 &
#70000000000
0)
01
02
00
0,
0+
b1001 /
b1001 3
b1001 5
b101 -
b101 4
b101 :
b101 ;
b1001 .
b1001 7
b1001 9
b1001 8
1"
b1110 &
#75000000000
0"
b1111 &
#80000000000
b1000 .
b1000 7
b1000 9
b1000 8
1"
b10000 &
#85000000000
0"
b10001 &
#90000000000
b111 .
b111 7
b111 9
b111 8
1"
b10010 &
#95000000000
0"
b10011 &
#100000000000
b110 .
b110 7
b110 9
b110 8
1"
b10100 &
#105000000000
0"
b10101 &
#110000000000
b101 .
b101 7
b101 9
b101 8
1"
b10110 &
#115000000000
0"
b10111 &
#116000000000
1!
#120000000000
b100 .
b100 7
b100 9
b100 8
1"
b11000 &
#124000000000
11
12
x)
10
1,
1+
b0 /
b0 3
b0 5
b0 -
b0 4
b0 :
b0 ;
b0 .
b0 7
b0 9
b0 8
0!
#125000000000
0"
b11001 &
#130000000000
0)
01
02
00
0,
0+
b1001 /
b1001 3
b1001 5
b101 -
b101 4
b101 :
b101 ;
b1001 .
b1001 7
b1001 9
b1001 8
1"
b11010 &
#135000000000
0"
b11011 &
#140000000000
b1000 .
b1000 7
b1000 9
b1000 8
1"
b11100 &
#145000000000
0"
b11101 &
#150000000000
b111 .
b111 7
b111 9
b111 8
1"
b11110 &
#155000000000
0"
b11111 &
#160000000000
b110 .
b110 7
b110 9
b110 8
1"
b100000 &
#165000000000
0"
b100001 &
#170000000000
b101 .
b101 7
b101 9
b101 8
1"
b100010 &
#175000000000
0"
b100011 &
#180000000000
b100 .
b100 7
b100 9
b100 8
1"
b100100 &
#185000000000
0"
b100101 &
#190000000000
b11 .
b11 7
b11 9
b11 8
1"
b100110 &
#195000000000
0"
b100111 &
#200000000000
b10 .
b10 7
b10 9
b10 8
1"
b101000 &
#205000000000
0"
b101001 &
#210000000000
b1 .
b1 7
b1 9
b1 8
1"
b101010 &
#215000000000
0"
b101011 &
#220000000000
10
x+
b0 .
b0 7
b0 9
b0 8
1"
b101100 &
#225000000000
0"
b101101 &
#230000000000
00
0+
b100 -
b100 4
b100 :
b100 ;
b1001 .
b1001 7
b1001 9
b1001 8
1"
b101110 &
#235000000000
0"
b101111 &
#240000000000
b1000 .
b1000 7
b1000 9
b1000 8
1"
b110000 &
#245000000000
0"
b110001 &
#250000000000
b111 .
b111 7
b111 9
b111 8
1"
b110010 &
#255000000000
0"
b110011 &
#260000000000
b110 .
b110 7
b110 9
b110 8
1"
b110100 &
#265000000000
0"
b110101 &
#270000000000
b101 .
b101 7
b101 9
b101 8
1"
b110110 &
#275000000000
0"
b110111 &
#280000000000
b100 .
b100 7
b100 9
b100 8
1"
b111000 &
#285000000000
0"
b111001 &
#290000000000
b11 .
b11 7
b11 9
b11 8
1"
b111010 &
#295000000000
0"
b111011 &
#300000000000
b10 .
b10 7
b10 9
b10 8
1"
b111100 &
#305000000000
0"
b111101 &
#310000000000
b1 .
b1 7
b1 9
b1 8
1"
b111110 &
#315000000000
0"
b111111 &
#320000000000
10
x+
b0 .
b0 7
b0 9
b0 8
1"
b1000000 &
#325000000000
0"
b1000001 &
#330000000000
00
0+
b11 -
b11 4
b11 :
b11 ;
b1001 .
b1001 7
b1001 9
b1001 8
1"
b1000010 &
#335000000000
0"
b1000011 &
#340000000000
b1000 .
b1000 7
b1000 9
b1000 8
1"
b1000100 &
#345000000000
0"
b1000101 &
#350000000000
b111 .
b111 7
b111 9
b111 8
1"
b1000110 &
#355000000000
0"
b1000111 &
#360000000000
b110 .
b110 7
b110 9
b110 8
1"
b1001000 &
#365000000000
0"
b1001001 &
#370000000000
b101 .
b101 7
b101 9
b101 8
1"
b1001010 &
#375000000000
0"
b1001011 &
#380000000000
b100 .
b100 7
b100 9
b100 8
1"
b1001100 &
#385000000000
0"
b1001101 &
#390000000000
b11 .
b11 7
b11 9
b11 8
1"
b1001110 &
#395000000000
0"
b1001111 &
#400000000000
b10 .
b10 7
b10 9
b10 8
1"
b1010000 &
#405000000000
0"
b1010001 &
#410000000000
b1 .
b1 7
b1 9
b1 8
1"
b1010010 &
#415000000000
0"
b1010011 &
#420000000000
10
x+
b0 .
b0 7
b0 9
b0 8
1"
b1010100 &
#425000000000
0"
b1010101 &
#430000000000
00
0+
b10 -
b10 4
b10 :
b10 ;
b1001 .
b1001 7
b1001 9
b1001 8
1"
b1010110 &
#435000000000
0"
b1010111 &
#440000000000
b1000 .
b1000 7
b1000 9
b1000 8
1"
b1011000 &
#445000000000
0"
b1011001 &
#450000000000
b111 .
b111 7
b111 9
b111 8
1"
b1011010 &
#455000000000
0"
b1011011 &
#460000000000
b110 .
b110 7
b110 9
b110 8
1"
b1011100 &
#465000000000
0"
b1011101 &
#470000000000
b101 .
b101 7
b101 9
b101 8
1"
b1011110 &
#475000000000
0"
b1011111 &
#480000000000
b100 .
b100 7
b100 9
b100 8
1"
b1100000 &
#485000000000
0"
b1100001 &
#490000000000
b11 .
b11 7
b11 9
b11 8
1"
b1100010 &
#495000000000
0"
b1100011 &
#500000000000
b10 .
b10 7
b10 9
b10 8
1"
b1100100 &
#505000000000
0"
b1100101 &
#510000000000
b1 .
b1 7
b1 9
b1 8
1"
b1100110 &
#515000000000
0"
b1100111 &
#520000000000
10
x+
b0 .
b0 7
b0 9
b0 8
1"
b1101000 &
#525000000000
0"
b1101001 &
#530000000000
00
0+
b1 -
b1 4
b1 :
b1 ;
b1001 .
b1001 7
b1001 9
b1001 8
1"
b1101010 &
#535000000000
0"
b1101011 &
#540000000000
b1000 .
b1000 7
b1000 9
b1000 8
1"
b1101100 &
#545000000000
0"
b1101101 &
#550000000000
b111 .
b111 7
b111 9
b111 8
1"
b1101110 &
#555000000000
0"
b1101111 &
#560000000000
b110 .
b110 7
b110 9
b110 8
1"
b1110000 &
#565000000000
0"
b1110001 &
#570000000000
b101 .
b101 7
b101 9
b101 8
1"
b1110010 &
#575000000000
0"
b1110011 &
#580000000000
b100 .
b100 7
b100 9
b100 8
1"
b1110100 &
#585000000000
0"
b1110101 &
#590000000000
b11 .
b11 7
b11 9
b11 8
1"
b1110110 &
#595000000000
0"
b1110111 &
#600000000000
b10 .
b10 7
b10 9
b10 8
1"
b1111000 &
#605000000000
0"
b1111001 &
#610000000000
b1 .
b1 7
b1 9
b1 8
1"
b1111010 &
#615000000000
0"
b1111011 &
#620000000000
10
x+
b0 .
b0 7
b0 9
b0 8
1"
b1111100 &
#625000000000
0"
b1111101 &
#630000000000
02
00
1,
0+
b0 -
b0 4
b0 :
b0 ;
b1001 .
b1001 7
b1001 9
b1001 8
1"
b1111110 &
#635000000000
0"
b1111111 &
#640000000000
b1000 .
b1000 7
b1000 9
b1000 8
1"
b10000000 &
#645000000000
0"
b10000001 &
#650000000000
b111 .
b111 7
b111 9
b111 8
1"
b10000010 &
#655000000000
0"
b10000011 &
#660000000000
b110 .
b110 7
b110 9
b110 8
1"
b10000100 &
#665000000000
0"
b10000101 &
#670000000000
b101 .
b101 7
b101 9
b101 8
1"
b10000110 &
#675000000000
0"
b10000111 &
#680000000000
b100 .
b100 7
b100 9
b100 8
1"
b10001000 &
#685000000000
0"
b10001001 &
#690000000000
b11 .
b11 7
b11 9
b11 8
1"
b10001010 &
#695000000000
0"
b10001011 &
#700000000000
b10 .
b10 7
b10 9
b10 8
1"
b10001100 &
#705000000000
0"
b10001101 &
#710000000000
b1 .
b1 7
b1 9
b1 8
1"
b10001110 &
#715000000000
0"
b10001111 &
#720000000000
12
x)
10
x+
b0 .
b0 7
b0 9
b0 8
1"
b10010000 &
#725000000000
0"
b10010001 &
#730000000000
0)
02
00
0,
0+
b1000 /
b1000 3
b1000 5
b101 -
b101 4
b101 :
b101 ;
b1001 .
b1001 7
b1001 9
b1001 8
1"
b10010010 &
#735000000000
0"
b10010011 &
#740000000000
b1000 .
b1000 7
b1000 9
b1000 8
1"
b10010100 &
#745000000000
0"
b10010101 &
#750000000000
b111 .
b111 7
b111 9
b111 8
1"
b10010110 &
#755000000000
0"
b10010111 &
#760000000000
b110 .
b110 7
b110 9
b110 8
1"
b10011000 &
#765000000000
0"
b10011001 &
#770000000000
b101 .
b101 7
b101 9
b101 8
1"
b10011010 &
#775000000000
0"
b10011011 &
#780000000000
b100 .
b100 7
b100 9
b100 8
1"
b10011100 &
#785000000000
0"
b10011101 &
#790000000000
b11 .
b11 7
b11 9
b11 8
1"
b10011110 &
#795000000000
0"
b10011111 &
#800000000000
b10 .
b10 7
b10 9
b10 8
1"
b10100000 &
#805000000000
0"
b10100001 &
#810000000000
b1 .
b1 7
b1 9
b1 8
1"
b10100010 &
#815000000000
0"
b10100011 &
#820000000000
10
x+
b0 .
b0 7
b0 9
b0 8
1"
b10100100 &
#825000000000
0"
b10100101 &
#830000000000
00
0+
b100 -
b100 4
b100 :
b100 ;
b1001 .
b1001 7
b1001 9
b1001 8
1"
b10100110 &
#835000000000
0"
b10100111 &
#840000000000
b1000 .
b1000 7
b1000 9
b1000 8
1"
b10101000 &
#845000000000
0"
b10101001 &
#850000000000
b111 .
b111 7
b111 9
b111 8
1"
b10101010 &
#855000000000
0"
b10101011 &
#860000000000
b110 .
b110 7
b110 9
b110 8
1"
b10101100 &
#865000000000
0"
b10101101 &
#870000000000
b101 .
b101 7
b101 9
b101 8
1"
b10101110 &
#875000000000
0"
b10101111 &
#880000000000
b100 .
b100 7
b100 9
b100 8
1"
b10110000 &
#885000000000
0"
b10110001 &
#890000000000
b11 .
b11 7
b11 9
b11 8
1"
b10110010 &
#895000000000
0"
b10110011 &
#900000000000
b10 .
b10 7
b10 9
b10 8
1"
b10110100 &
#905000000000
0"
b10110101 &
#910000000000
b1 .
b1 7
b1 9
b1 8
1"
b10110110 &
#915000000000
0"
b10110111 &
#920000000000
10
x+
b0 .
b0 7
b0 9
b0 8
1"
b10111000 &
#925000000000
0"
b10111001 &
#930000000000
00
0+
b11 -
b11 4
b11 :
b11 ;
b1001 .
b1001 7
b1001 9
b1001 8
1"
b10111010 &
#935000000000
0"
b10111011 &
#940000000000
b1000 .
b1000 7
b1000 9
b1000 8
1"
b10111100 &
#945000000000
0"
b10111101 &
#950000000000
b111 .
b111 7
b111 9
b111 8
1"
b10111110 &
#955000000000
0"
b10111111 &
#960000000000
b110 .
b110 7
b110 9
b110 8
1"
b11000000 &
#965000000000
0"
b11000001 &
#970000000000
b101 .
b101 7
b101 9
b101 8
1"
b11000010 &
#975000000000
0"
b11000011 &
#980000000000
b100 .
b100 7
b100 9
b100 8
1"
b11000100 &
#985000000000
0"
b11000101 &
#990000000000
b11 .
b11 7
b11 9
b11 8
1"
b11000110 &
#995000000000
0"
b11000111 &
#1000000000000
b10 .
b10 7
b10 9
b10 8
1"
b11001000 &
#1005000000000
0"
b11001001 &
#1010000000000
b1 .
b1 7
b1 9
b1 8
1"
b11001010 &
#1015000000000
0"
b11001011 &
#1020000000000
10
x+
b0 .
b0 7
b0 9
b0 8
1"
b11001100 &
#1025000000000
0"
b11001101 &
#1030000000000
00
0+
b10 -
b10 4
b10 :
b10 ;
b1001 .
b1001 7
b1001 9
b1001 8
1"
b11001110 &
#1035000000000
0"
b11001111 &
#1040000000000
b1000 .
b1000 7
b1000 9
b1000 8
1"
b11010000 &
#1045000000000
0"
b11010001 &
#1050000000000
b111 .
b111 7
b111 9
b111 8
1"
b11010010 &
#1055000000000
0"
b11010011 &
#1060000000000
b110 .
b110 7
b110 9
b110 8
1"
b11010100 &
#1065000000000
0"
b11010101 &
#1070000000000
b101 .
b101 7
b101 9
b101 8
1"
b11010110 &
#1075000000000
0"
b11010111 &
#1080000000000
b100 .
b100 7
b100 9
b100 8
1"
b11011000 &
#1085000000000
0"
b11011001 &
#1090000000000
b11 .
b11 7
b11 9
b11 8
1"
b11011010 &
#1095000000000
0"
b11011011 &
#1100000000000
b10 .
b10 7
b10 9
b10 8
1"
b11011100 &
#1105000000000
0"
b11011101 &
#1110000000000
b1 .
b1 7
b1 9
b1 8
1"
b11011110 &
#1115000000000
0"
b11011111 &
#1120000000000
10
x+
b0 .
b0 7
b0 9
b0 8
1"
b11100000 &
#1125000000000
0"
b11100001 &
#1130000000000
00
0+
b1 -
b1 4
b1 :
b1 ;
b1001 .
b1001 7
b1001 9
b1001 8
1"
b11100010 &
#1135000000000
0"
b11100011 &
#1140000000000
b1000 .
b1000 7
b1000 9
b1000 8
1"
b11100100 &
#1145000000000
0"
b11100101 &
#1150000000000
b111 .
b111 7
b111 9
b111 8
1"
b11100110 &
#1155000000000
0"
b11100111 &
#1160000000000
b110 .
b110 7
b110 9
b110 8
1"
b11101000 &
#1165000000000
0"
b11101001 &
#1170000000000
b101 .
b101 7
b101 9
b101 8
1"
b11101010 &
#1175000000000
0"
b11101011 &
#1180000000000
b100 .
b100 7
b100 9
b100 8
1"
b11101100 &
#1185000000000
0"
b11101101 &
#1190000000000
b11 .
b11 7
b11 9
b11 8
1"
b11101110 &
#1195000000000
0"
b11101111 &
#1200000000000
b10 .
b10 7
b10 9
b10 8
1"
b11110000 &
#1205000000000
0"
b11110001 &
#1210000000000
b1 .
b1 7
b1 9
b1 8
1"
b11110010 &
#1215000000000
0"
b11110011 &
#1220000000000
10
x+
b0 .
b0 7
b0 9
b0 8
1"
b11110100 &
#1225000000000
0"
b11110101 &
#1230000000000
02
00
1,
0+
b0 -
b0 4
b0 :
b0 ;
b1001 .
b1001 7
b1001 9
b1001 8
1"
b11110110 &
#1235000000000
0"
b11110111 &
#1240000000000
b1000 .
b1000 7
b1000 9
b1000 8
1"
b11111000 &
#1245000000000
0"
b11111001 &
#1250000000000
b111 .
b111 7
b111 9
b111 8
1"
b11111010 &
#1255000000000
0"
b11111011 &
#1260000000000
b110 .
b110 7
b110 9
b110 8
1"
b11111100 &
#1265000000000
0"
b11111101 &
#1270000000000
b101 .
b101 7
b101 9
b101 8
1"
b11111110 &
#1275000000000
0"
b11111111 &
#1280000000000
b100 .
b100 7
b100 9
b100 8
1"
b100000000 &
#1285000000000
0"
b100000001 &
#1290000000000
b11 .
b11 7
b11 9
b11 8
1"
b100000010 &
#1295000000000
0"
b100000011 &
#1300000000000
b10 .
b10 7
b10 9
b10 8
1"
b100000100 &
#1305000000000
0"
b100000101 &
#1310000000000
b1 .
b1 7
b1 9
b1 8
1"
b100000110 &
#1315000000000
0"
b100000111 &
#1320000000000
12
x)
10
x+
b0 .
b0 7
b0 9
b0 8
1"
b100001000 &
#1325000000000
0"
b100001001 &
#1330000000000
0)
02
00
0,
0+
b111 /
b111 3
b111 5
b101 -
b101 4
b101 :
b101 ;
b1001 .
b1001 7
b1001 9
b1001 8
1"
b100001010 &
#1335000000000
0"
b100001011 &
#1340000000000
b1000 .
b1000 7
b1000 9
b1000 8
1"
b100001100 &
#1345000000000
0"
b100001101 &
#1350000000000
b111 .
b111 7
b111 9
b111 8
1"
b100001110 &
#1355000000000
0"
b100001111 &
#1360000000000
b110 .
b110 7
b110 9
b110 8
1"
b100010000 &
#1365000000000
0"
b100010001 &
#1370000000000
b101 .
b101 7
b101 9
b101 8
1"
b100010010 &
#1375000000000
0"
b100010011 &
#1380000000000
b100 .
b100 7
b100 9
b100 8
1"
b100010100 &
#1385000000000
0"
b100010101 &
#1390000000000
b11 .
b11 7
b11 9
b11 8
1"
b100010110 &
#1395000000000
0"
b100010111 &
#1400000000000
b10 .
b10 7
b10 9
b10 8
1"
b100011000 &
#1405000000000
0"
b100011001 &
#1410000000000
b1 .
b1 7
b1 9
b1 8
1"
b100011010 &
#1415000000000
0"
b100011011 &
#1420000000000
10
x+
b0 .
b0 7
b0 9
b0 8
1"
b100011100 &
#1425000000000
0"
b100011101 &
#1430000000000
00
0+
b100 -
b100 4
b100 :
b100 ;
b1001 .
b1001 7
b1001 9
b1001 8
1"
b100011110 &
#1435000000000
0"
b100011111 &
#1440000000000
b1000 .
b1000 7
b1000 9
b1000 8
1"
b100100000 &
#1445000000000
0"
b100100001 &
#1450000000000
b111 .
b111 7
b111 9
b111 8
1"
b100100010 &
#1455000000000
0"
b100100011 &
#1460000000000
b110 .
b110 7
b110 9
b110 8
1"
b100100100 &
#1465000000000
0"
b100100101 &
#1470000000000
b101 .
b101 7
b101 9
b101 8
1"
b100100110 &
#1475000000000
0"
b100100111 &
#1480000000000
b100 .
b100 7
b100 9
b100 8
1"
b100101000 &
#1485000000000
0"
b100101001 &
#1490000000000
b11 .
b11 7
b11 9
b11 8
1"
b100101010 &
#1495000000000
0"
b100101011 &
#1500000000000
b10 .
b10 7
b10 9
b10 8
1"
b100101100 &
#1505000000000
0"
b100101101 &
#1510000000000
b1 .
b1 7
b1 9
b1 8
1"
b100101110 &
#1515000000000
0"
b100101111 &
#1520000000000
10
x+
b0 .
b0 7
b0 9
b0 8
1"
b100110000 &
#1525000000000
0"
b100110001 &
#1530000000000
00
0+
b11 -
b11 4
b11 :
b11 ;
b1001 .
b1001 7
b1001 9
b1001 8
1"
b100110010 &
#1535000000000
0"
b100110011 &
#1540000000000
b1000 .
b1000 7
b1000 9
b1000 8
1"
b100110100 &
#1545000000000
0"
b100110101 &
#1550000000000
b111 .
b111 7
b111 9
b111 8
1"
b100110110 &
#1555000000000
0"
b100110111 &
#1560000000000
b110 .
b110 7
b110 9
b110 8
1"
b100111000 &
#1565000000000
0"
b100111001 &
#1570000000000
b101 .
b101 7
b101 9
b101 8
1"
b100111010 &
#1575000000000
0"
b100111011 &
#1580000000000
b100 .
b100 7
b100 9
b100 8
1"
b100111100 &
#1585000000000
0"
b100111101 &
#1590000000000
b11 .
b11 7
b11 9
b11 8
1"
b100111110 &
#1595000000000
0"
b100111111 &
#1600000000000
b10 .
b10 7
b10 9
b10 8
1"
b101000000 &
#1605000000000
0"
b101000001 &
#1610000000000
b1 .
b1 7
b1 9
b1 8
1"
b101000010 &
#1615000000000
0"
b101000011 &
#1620000000000
10
x+
b0 .
b0 7
b0 9
b0 8
1"
b101000100 &
#1625000000000
0"
b101000101 &
#1630000000000
00
0+
b10 -
b10 4
b10 :
b10 ;
b1001 .
b1001 7
b1001 9
b1001 8
1"
b101000110 &
#1635000000000
0"
b101000111 &
#1640000000000
b1000 .
b1000 7
b1000 9
b1000 8
1"
b101001000 &
#1645000000000
0"
b101001001 &
#1650000000000
b111 .
b111 7
b111 9
b111 8
1"
b101001010 &
#1655000000000
0"
b101001011 &
#1660000000000
b110 .
b110 7
b110 9
b110 8
1"
b101001100 &
#1665000000000
0"
b101001101 &
#1670000000000
b101 .
b101 7
b101 9
b101 8
1"
b101001110 &
#1675000000000
0"
b101001111 &
#1680000000000
b100 .
b100 7
b100 9
b100 8
1"
b101010000 &
#1685000000000
0"
b101010001 &
#1690000000000
b11 .
b11 7
b11 9
b11 8
1"
b101010010 &
#1695000000000
0"
b101010011 &
#1700000000000
b10 .
b10 7
b10 9
b10 8
1"
b101010100 &
#1705000000000
0"
b101010101 &
#1710000000000
b1 .
b1 7
b1 9
b1 8
1"
b101010110 &
#1715000000000
0"
b101010111 &
#1720000000000
10
x+
b0 .
b0 7
b0 9
b0 8
1"
b101011000 &
#1725000000000
0"
b101011001 &
#1730000000000
00
0+
b1 -
b1 4
b1 :
b1 ;
b1001 .
b1001 7
b1001 9
b1001 8
1"
b101011010 &
#1735000000000
0"
b101011011 &
#1740000000000
b1000 .
b1000 7
b1000 9
b1000 8
1"
b101011100 &
#1745000000000
0"
b101011101 &
#1750000000000
b111 .
b111 7
b111 9
b111 8
1"
b101011110 &
#1755000000000
0"
b101011111 &
#1760000000000
b110 .
b110 7
b110 9
b110 8
1"
b101100000 &
#1765000000000
0"
b101100001 &
#1770000000000
b101 .
b101 7
b101 9
b101 8
1"
b101100010 &
#1775000000000
0"
b101100011 &
#1780000000000
b100 .
b100 7
b100 9
b100 8
1"
b101100100 &
#1785000000000
0"
b101100101 &
#1790000000000
b11 .
b11 7
b11 9
b11 8
1"
b101100110 &
#1795000000000
0"
b101100111 &
#1800000000000
b10 .
b10 7
b10 9
b10 8
1"
b101101000 &
#1805000000000
0"
b101101001 &
#1810000000000
b1 .
b1 7
b1 9
b1 8
1"
b101101010 &
#1815000000000
0"
b101101011 &
#1820000000000
10
x+
b0 .
b0 7
b0 9
b0 8
1"
b101101100 &
#1825000000000
0"
b101101101 &
#1830000000000
02
00
1,
0+
b0 -
b0 4
b0 :
b0 ;
b1001 .
b1001 7
b1001 9
b1001 8
1"
b101101110 &
#1835000000000
0"
b101101111 &
#1840000000000
b1000 .
b1000 7
b1000 9
b1000 8
1"
b101110000 &
#1845000000000
0"
b101110001 &
#1850000000000
b111 .
b111 7
b111 9
b111 8
1"
b101110010 &
#1855000000000
0"
b101110011 &
#1860000000000
b110 .
b110 7
b110 9
b110 8
1"
b101110100 &
#1865000000000
0"
b101110101 &
#1870000000000
b101 .
b101 7
b101 9
b101 8
1"
b101110110 &
#1875000000000
0"
b101110111 &
#1880000000000
b100 .
b100 7
b100 9
b100 8
1"
b101111000 &
#1885000000000
0"
b101111001 &
#1890000000000
b11 .
b11 7
b11 9
b11 8
1"
b101111010 &
#1895000000000
0"
b101111011 &
#1900000000000
b10 .
b10 7
b10 9
b10 8
1"
b101111100 &
#1905000000000
0"
b101111101 &
#1910000000000
b1 .
b1 7
b1 9
b1 8
1"
b101111110 &
#1915000000000
0"
b101111111 &
#1920000000000
12
x)
10
x+
b0 .
b0 7
b0 9
b0 8
1"
b110000000 &
#1925000000000
0"
b110000001 &
#1930000000000
0)
02
00
0,
0+
b110 /
b110 3
b110 5
b101 -
b101 4
b101 :
b101 ;
b1001 .
b1001 7
b1001 9
b1001 8
1"
b110000010 &
#1935000000000
0"
b110000011 &
#1940000000000
b1000 .
b1000 7
b1000 9
b1000 8
1"
b110000100 &
#1945000000000
0"
b110000101 &
#1950000000000
b111 .
b111 7
b111 9
b111 8
1"
b110000110 &
#1955000000000
0"
b110000111 &
#1960000000000
b110 .
b110 7
b110 9
b110 8
1"
b110001000 &
#1965000000000
0"
b110001001 &
#1970000000000
b101 .
b101 7
b101 9
b101 8
1"
b110001010 &
#1975000000000
0"
b110001011 &
#1980000000000
b100 .
b100 7
b100 9
b100 8
1"
b110001100 &
#1985000000000
0"
b110001101 &
#1990000000000
b11 .
b11 7
b11 9
b11 8
1"
b110001110 &
#1995000000000
0"
b110001111 &
#2000000000000
b10 .
b10 7
b10 9
b10 8
1"
b110010000 &
#2005000000000
0"
b110010001 &
#2010000000000
b1 .
b1 7
b1 9
b1 8
1"
b110010010 &
#2015000000000
0"
b110010011 &
#2020000000000
10
x+
b0 .
b0 7
b0 9
b0 8
1"
b110010100 &
#2025000000000
0"
b110010101 &
#2030000000000
00
0+
b100 -
b100 4
b100 :
b100 ;
b1001 .
b1001 7
b1001 9
b1001 8
1"
b110010110 &
#2035000000000
0"
b110010111 &
#2040000000000
b1000 .
b1000 7
b1000 9
b1000 8
1"
b110011000 &
#2045000000000
0"
b110011001 &
#2050000000000
b111 .
b111 7
b111 9
b111 8
1"
b110011010 &
#2055000000000
0"
b110011011 &
#2060000000000
b110 .
b110 7
b110 9
b110 8
1"
b110011100 &
#2065000000000
0"
b110011101 &
#2070000000000
b101 .
b101 7
b101 9
b101 8
1"
b110011110 &
#2075000000000
0"
b110011111 &
#2080000000000
b100 .
b100 7
b100 9
b100 8
1"
b110100000 &
#2085000000000
0"
b110100001 &
#2090000000000
b11 .
b11 7
b11 9
b11 8
1"
b110100010 &
#2095000000000
0"
b110100011 &
#2100000000000
b10 .
b10 7
b10 9
b10 8
1"
b110100100 &
#2105000000000
0"
b110100101 &
#2110000000000
b1 .
b1 7
b1 9
b1 8
1"
b110100110 &
#2115000000000
0"
b110100111 &
#2120000000000
10
x+
b0 .
b0 7
b0 9
b0 8
1"
b110101000 &
#2125000000000
0"
b110101001 &
