hdl/control/latchsr.v
module latchsr (
    output wire Q,
    input wire  R, S 
);
    reg rQ = 0; 
    assign Q = rQ; 

    always @(S,R) begin
        if(S && R || !S && !R)
        begin
            // fazer nada
        end
        else if(!S && R) begin
            rQ = 0;
        end
        else if(S && !R) begin
            rQ = 1;
        end
    end
endmodule

hdl/control/latchsr_tb.v
`timescale 1ns/1ps
module latchsr_tb();

	reg R_TB, S_TB;
	wire Q_TB;

	latchsr DUT(.R(R_TB), .S(S_TB), .Q(Q_TB));
	initial
		begin
		
			$dumpfile("latchsr_tb.vcd");
			$dumpvars(0,latchsr_tb);
			    S_TB=0; R_TB=0;
			#10 S_TB=0; R_TB=0;
			#10 S_TB=0; R_TB=1;
			#10 S_TB=0; R_TB=1;
			#10 S_TB=1; R_TB=0;
			#10 S_TB=1; R_TB=0;
			#10 S_TB=0; R_TB=0;
		end

endmodule

hdl/control/control.v
module control (
    input wire startn , stopn , clearn, door_closed, timer_done, 
    output wire mag_on
); 
    wire rS, rR;
    wire rQ;
      
    assign rS = (!startn  && door_closed) ? 1 : 0;
    assign rR = (!stopn || timer_done || !door_closed || !clearn) ? 1 : 0;

    latchsr LSR_ON(.Q(rQ), .S(rS), .R(rR)); 

    assign mag_on = rQ;  
    
endmodule

test/control_tb.v
`timescale 1ns/1ps
module control_tb();


    //startn , stopn , clearn, door_closed, timer_done, 
	reg startn_TB, stopn_TB, clearn_TB , doorClosed_TB, timerDone_TB;
	wire magOn_TB;

	control DUT(
        .startn(startn_TB), .stopn(stopn_TB), .clearn(clearn_TB),
        .door_closed(doorClosed_TB) , .timer_done(timerDone_TB),
        .mag_on(magOn_TB)  
    );
	initial
		begin
		
			$dumpfile("control_tb.vcd");
			$dumpvars(0,control_tb);

			    startn_TB=0; stopn_TB=0; clearn_TB=0; timerDone_TB=0; doorClosed_TB=0;   

			    #10 startn_TB=1; stopn_TB=1; clearn_TB=0; timerDone_TB=0; doorClosed_TB=0;   
			    #10 startn_TB=1; stopn_TB=1; clearn_TB=0; timerDone_TB=0; doorClosed_TB=1;   
			    #10 startn_TB=1; stopn_TB=1; clearn_TB=0; timerDone_TB=1; doorClosed_TB=0;   
			    #10 startn_TB=1; stopn_TB=1; clearn_TB=0; timerDone_TB=1; doorClosed_TB=1;   
			    #10 startn_TB=1; stopn_TB=1; clearn_TB=1; timerDone_TB=0; doorClosed_TB=0;   
			    #10 startn_TB=1; stopn_TB=1; clearn_TB=1; timerDone_TB=0; doorClosed_TB=1;   
			    #10 startn_TB=1; stopn_TB=1; clearn_TB=1; timerDone_TB=1; doorClosed_TB=0;   
			    #10 startn_TB=1; stopn_TB=1; clearn_TB=1; timerDone_TB=1; doorClosed_TB=1;   

			    #10 startn_TB=1; stopn_TB=1; clearn_TB=0; timerDone_TB=0; doorClosed_TB=0;   
			    #10 startn_TB=1; stopn_TB=1; clearn_TB=0; timerDone_TB=0; doorClosed_TB=1;   
			    #10 startn_TB=1; stopn_TB=1; clearn_TB=0; timerDone_TB=1; doorClosed_TB=0;   
			    #10 startn_TB=1; stopn_TB=1; clearn_TB=0; timerDone_TB=1; doorClosed_TB=1;   
			    #10 startn_TB=1; stopn_TB=1; clearn_TB=1; timerDone_TB=0; doorClosed_TB=0;   
			    #10 startn_TB=1; stopn_TB=1; clearn_TB=1; timerDone_TB=0; doorClosed_TB=1;   
			    #10 startn_TB=1; stopn_TB=1; clearn_TB=1; timerDone_TB=1; doorClosed_TB=0;   
			    #10 startn_TB=1; stopn_TB=1; clearn_TB=1; timerDone_TB=1; doorClosed_TB=1;   

			    #10 startn_TB=1; stopn_TB=1; clearn_TB=1; timerDone_TB=1; doorClosed_TB=0;   
			    #10 startn_TB=1; stopn_TB=1; clearn_TB=1; timerDone_TB=1; doorClosed_TB=0;   
			    #10 startn_TB=1; stopn_TB=1; clearn_TB=1; timerDone_TB=1; doorClosed_TB=0;   
			    #10 startn_TB=1; stopn_TB=1; clearn_TB=1; timerDone_TB=0; doorClosed_TB=0;   
			    #10 startn_TB=1; stopn_TB=1; clearn_TB=1; timerDone_TB=0; doorClosed_TB=0;   
			    #10 startn_TB=1; stopn_TB=0; clearn_TB=1; timerDone_TB=0; doorClosed_TB=0;   
			    #10 startn_TB=1; stopn_TB=0; clearn_TB=1; timerDone_TB=0; doorClosed_TB=0;   
			    #10 startn_TB=1; stopn_TB=0; clearn_TB=1; timerDone_TB=0; doorClosed_TB=0;   

			    #10 startn_TB=0; stopn_TB=1; clearn_TB=1; timerDone_TB=0; doorClosed_TB=0;   
			    #10 startn_TB=0; stopn_TB=1; clearn_TB=1; timerDone_TB=0; doorClosed_TB=1;   
			    #10 startn_TB=0; stopn_TB=1; clearn_TB=1; timerDone_TB=1; doorClosed_TB=0;   
			    #10 startn_TB=0; stopn_TB=1; clearn_TB=1; timerDone_TB=1; doorClosed_TB=1;   
			    #10 startn_TB=0; stopn_TB=1; clearn_TB=1; timerDone_TB=0; doorClosed_TB=0;   
			    #10 startn_TB=1; stopn_TB=1; clearn_TB=1; timerDone_TB=0; doorClosed_TB=1;   
			    #10 startn_TB=1; stopn_TB=1; clearn_TB=1; timerDone_TB=1; doorClosed_TB=0;   
			    #10 startn_TB=1; stopn_TB=1; clearn_TB=1; timerDone_TB=1; doorClosed_TB=1;   

			    #10 startn_TB=1; stopn_TB=1; clearn_TB=1; timerDone_TB=0; doorClosed_TB=1;   
			    #50 startn_TB=0; stopn_TB=1; clearn_TB=1; timerDone_TB=0; doorClosed_TB=1;   
			    #5 startn_TB=1; stopn_TB=1; clearn_TB=1; timerDone_TB=0; doorClosed_TB=1;   
			    #50 startn_TB=1; stopn_TB=1; clearn_TB=1; timerDone_TB=1; doorClosed_TB=1;   
			    #50 startn_TB=1; stopn_TB=1; clearn_TB=1; timerDone_TB=1; doorClosed_TB=0;   


		end

endmodule

control_tb.vcd
$date
	Thu Apr 29 22:49:41 2021
$end
$version
	Icarus Verilog
$end
$timescale
	1ps
$end
$scope module control_tb $end
$var wire 1 ! magOn_TB $end
$var reg 1 " clearn_TB $end
$var reg 1 # doorClosed_TB $end
$var reg 1 $ startn_TB $end
$var reg 1 % stopn_TB $end
$var reg 1 & timerDone_TB $end
$scope module DUT $end
$var wire 1 " clearn $end
$var wire 1 # door_closed $end
$var wire 1 ! mag_on $end
$var wire 1 $ startn $end
$var wire 1 % stopn $end
$var wire 1 & timer_done $end
$var wire 1 ' rS $end
$var wire 1 ( rR $end
$var wire 1 ) rQ $end
$scope module LSR_ON $end
$var wire 1 ( R $end
$var wire 1 ' S $end
$var wire 1 ) Q $end
$var reg 1 ) rQ $end
$upscope $end
$upscope $end
$upscope $end
$scope module latchsr_tb $end
$var wire 1 * Q_TB $end
$var reg 1 + R_TB $end
$var reg 1 , S_TB $end
$scope module DUT $end
$var wire 1 * Q $end
$var wire 1 + R $end
$var wire 1 , S $end
$var reg 1 - rQ $end
$upscope $end
$upscope $end
$enddefinitions $end
#0
$dumpvars
0-
0,
0+
0*
0)
1(
0'
0&
0%
0$
0#
0"
0!
$end
#10000
1%
1$
#20000
1+
1#
#30000
0#
1&
#40000
1*
1-
0+
1,
1#
#50000
0#
0&
1"
#60000
0(
0,
1#
#70000
1(
1,
0#
1&
#80000
1#
#90000
0#
0&
0"
#100000
1#
#110000
0#
1&
#120000
0*
0-
1+
0,
1#
#130000
0#
0&
1"
#140000
0(
0+
1#
#150000
1(
0#
1&
#160000
1#
#170000
0#
#200000
0&
#220000
0%
#250000
1%
0$
#260000
1!
1)
0(
1'
1#
#270000
0!
0)
1(
0'
0#
1&
#280000
1'
1#
#290000
0'
0#
0&
#300000
0(
1#
1$
#310000
1(
0#
1&
#320000
1#
#330000
0(
0&
#380000
1!
1)
1'
0$
#385000
0'
1$
#435000
0!
0)
1(
1&
#485000
0#
