hdl/decoder/decoder.v
module  decoder (
    input wire [3:0] sec_ones,
    input wire [3:0] sec_tens,
    input wire [3:0] min,
    output wire [6:0] sec_ones_segs ,
    output wire [6:0] sec_tens_segs ,
    output wire [6:0] min_segs    
);

    assign sec_ones_segs =(sec_ones == 4'b0000)? 7'b1111110: // 0 
                          (sec_ones == 4'b0001)? 7'b0110000: // 1
                          (sec_ones == 4'b0010)? 7'b1101101: // 2 
                          (sec_ones == 4'b0011)? 7'b1111001: // 3
                          (sec_ones == 4'b0100)? 7'b0110011: // 4
                          (sec_ones == 4'b0101)? 7'b1011011: // 5
                          (sec_ones == 4'b0110)? 7'b1011111: // 6
                          (sec_ones == 4'b0111)? 7'b1110000: // 7
                          (sec_ones == 4'b1000)? 7'b1111111: // 8
                          (sec_ones == 4'b1001)? 7'b1110011: // 9
                          8'bXXXX_XXXX ;
    assign sec_tens_segs =(sec_tens == 4'b0000)? 7'b1111110: // 0 
                          (sec_tens == 4'b0001)? 7'b0110000: // 1
                          (sec_tens == 4'b0010)? 7'b1101101: // 2 
                          (sec_tens == 4'b0011)? 7'b1111001: // 3
                          (sec_tens == 4'b0100)? 7'b0110011: // 4
                          (sec_tens == 4'b0101)? 7'b1011011: // 5
                          (sec_tens == 4'b0110)? 7'b1011111: // 6
                          (sec_tens == 4'b0111)? 7'b1110000: // 7
                          (sec_tens == 4'b1000)? 7'b1111111: // 8
                          (sec_tens == 4'b1001)? 7'b1110011: // 9
                          8'bXXXX_XXXX ;

    assign min_segs =     (min == 4'b0000)? 7'b1111110: // 0 
                          (min == 4'b0001)? 7'b0110000: // 1
                          (min == 4'b0010)? 7'b1101101: // 2 
                          (min == 4'b0011)? 7'b1111001: // 3
                          (min == 4'b0100)? 7'b0110011: // 4
                          (min == 4'b0101)? 7'b1011011: // 5
                          (min == 4'b0110)? 7'b1011111: // 6
                          (min == 4'b0111)? 7'b1110000: // 7
                          (min == 4'b1000)? 7'b1111111: // 8
                          (min == 4'b1001)? 7'b1110011: // 9
                          8'bXXXX_XXXX ; 
    
endmodule

test/decoder_tb.v
`timescale 1ns/1ps
module decoder_tb();

    /*
        module  decoder (
        input wire [3:0] sec_ones,
        input wire [3:0] sec_tens,
        input wire [3:0] min,
        output wire [6:0] sec_ones_segs ,
        output wire [6:0] sec_tens_segs ,
        output wire [6:0] min_segs    
    );
    */

    //sec_ones , sec_tens , min, door_closed, timer_done, 
	reg [3:0 ]sec_ones_TB, sec_tens_TB, min_TB ;
    wire [6:0] min_segs_TB , sec_ones_seg_TB , sec_tens_seg_TB ;

	decoder DUT(
        .sec_ones(sec_ones_TB), .sec_tens(sec_tens_TB), .min(min_TB),
        .sec_ones_segs(sec_ones_seg_TB) , .sec_tens_segs(sec_tens_seg_TB),
        .min_segs(min_segs_TB)  
    );
	initial
		begin
		
			$dumpfile("decoder_tb.vcd");
			$dumpvars(0,decoder_tb);

			    sec_ones_TB=0; sec_tens_TB=0; min_TB=0;    

			    #10 sec_ones_TB=1; sec_tens_TB=1; min_TB=0;    
			    #10 sec_ones_TB=1; sec_tens_TB=1; min_TB=0;    
			    #10 sec_ones_TB=1; sec_tens_TB=1; min_TB=0;    
			    #10 sec_ones_TB=1; sec_tens_TB=1; min_TB=0;    
			    #10 sec_ones_TB=1; sec_tens_TB=1; min_TB=1;    
			    #10 sec_ones_TB=1; sec_tens_TB=1; min_TB=1;    
			    #10 sec_ones_TB=1; sec_tens_TB=1; min_TB=1;    
			    #10 sec_ones_TB=1; sec_tens_TB=1; min_TB=1;    

			    #10 sec_ones_TB=1; sec_tens_TB=1; min_TB=0;    
			    #10 sec_ones_TB=1; sec_tens_TB=1; min_TB=0;    
			    #10 sec_ones_TB=1; sec_tens_TB=1; min_TB=0;    
			    #10 sec_ones_TB=1; sec_tens_TB=1; min_TB=0;    
			    #10 sec_ones_TB=1; sec_tens_TB=1; min_TB=1;    
			    #10 sec_ones_TB=1; sec_tens_TB=1; min_TB=1;    
			    #10 sec_ones_TB=1; sec_tens_TB=1; min_TB=1;    
			    #10 sec_ones_TB=1; sec_tens_TB=1; min_TB=1;    

			    #10 sec_ones_TB=1; sec_tens_TB=1; min_TB=1;    
			    #10 sec_ones_TB=1; sec_tens_TB=1; min_TB=1;    
			    #10 sec_ones_TB=1; sec_tens_TB=1; min_TB=1;    
			    #10 sec_ones_TB=1; sec_tens_TB=1; min_TB=1;    
			    #10 sec_ones_TB=1; sec_tens_TB=1; min_TB=1;    
			    #10 sec_ones_TB=1; sec_tens_TB=0; min_TB=1;    
			    #10 sec_ones_TB=1; sec_tens_TB=0; min_TB=1;    
			    #10 sec_ones_TB=1; sec_tens_TB=0; min_TB=1;    

			    #10 sec_ones_TB=0; sec_tens_TB=1; min_TB=1;    
			    #10 sec_ones_TB=0; sec_tens_TB=1; min_TB=1;    
			    #10 sec_ones_TB=0; sec_tens_TB=1; min_TB=1;    
			    #10 sec_ones_TB=0; sec_tens_TB=1; min_TB=1;    
			    #10 sec_ones_TB=0; sec_tens_TB=1; min_TB=1;    
			    #10 sec_ones_TB=1; sec_tens_TB=1; min_TB=1;    
			    #10 sec_ones_TB=1; sec_tens_TB=1; min_TB=1;    
			    #10 sec_ones_TB=1; sec_tens_TB=1; min_TB=1;    

			    #10 sec_ones_TB=1; sec_tens_TB=1; min_TB=1;   
			    #50 sec_ones_TB=0; sec_tens_TB=1; min_TB=1;   
			    #5 sec_ones_TB=1; sec_tens_TB=1; min_TB=1;   
			    #50 sec_ones_TB=1; sec_tens_TB=1; min_TB=1;   
			    #50 sec_ones_TB=1; sec_tens_TB=1; min_TB=1;   


		end

endmodule

decoder_tb.vcd
$date
	Thu Apr 29 23:59:05 2021
$end
$version
	Icarus Verilog
$end
$timescale
	1ps
$end
$scope module decoder_tb $end
$var wire 7 ! sec_tens_seg_TB [6:0] $end
$var wire 7 " sec_ones_seg_TB [6:0] $end
$var wire 7 # min_segs_TB [6:0] $end
$var reg 4 $ min_TB [3:0] $end
$var reg 4 % sec_ones_TB [3:0] $end
$var reg 4 & sec_tens_TB [3:0] $end
$scope module DUT $end
$var wire 4 ' min [3:0] $end
$var wire 4 ( sec_ones [3:0] $end
$var wire 4 ) sec_tens [3:0] $end
$var wire 7 * sec_tens_segs [6:0] $end
$var wire 7 + sec_ones_segs [6:0] $end
$var wire 7 , min_segs [6:0] $end
$upscope $end
$upscope $end
$enddefinitions $end
#0
$dumpvars
b1111110 ,
b1111110 +
b1111110 *
b0 )
b0 (
b0 '
b0 &
b0 %
b0 $
b1111110 #
b1111110 "
b1111110 !
$end
#10000
b110000 !
b110000 *
b110000 "
b110000 +
b1 &
b1 )
b1 %
b1 (
#50000
b110000 #
b110000 ,
b1 $
b1 '
#90000
b1111110 #
b1111110 ,
b0 $
b0 '
#130000
b110000 #
b110000 ,
b1 $
b1 '
#220000
b1111110 !
b1111110 *
b0 &
b0 )
#250000
b110000 !
b110000 *
b1111110 "
b1111110 +
b1 &
b1 )
b0 %
b0 (
#300000
b110000 "
b110000 +
b1 %
b1 (
#380000
b1111110 "
b1111110 +
b0 %
b0 (
#385000
b110000 "
b110000 +
b1 %
b1 (
