hdl/control/latchsr.v
module latchsr (
    output wire Q,
    input wire  R, S 
);
    reg rQ , rQn ; 
    always @(R,S) begin
        if(R != S || S == 0 )
        begin
            rQ  = !(R && rQn);
            rQn = !(S && rQ);             
        end
    end
    assign Q = rQ; 
endmodule

hdl/control/latchsr_tb.v
`timescale 1ns/1ps
module latchsr_tb();

	reg R_TB, S_TB;
	wire Q_TB;

	latchsr DUT(.R(R_TB), .S(S_TB), .Q(Q_TB));
	initial
		begin
		
			$dumpfile("latchsr_tb.vcd");
			$dumpvars(0,latchsr_tb);
			    S_TB=0; R_TB=0;
			#10 S_TB=0; R_TB=0;
			#10 S_TB=0; R_TB=1;
			#10 S_TB=0; R_TB=1;
			#10 S_TB=1; R_TB=0;
			#10 S_TB=1; R_TB=0;
			#10 S_TB=0; R_TB=0;
		end

endmodule

hdl/control/control.v
module control (
    input wire startn , stopn , clearn, door_closed, timer_done, 
    output reg mag_on
); 

    reg rS  = 0 , rR =0  ;
    wire rQ  ; 
    latchsr LSR_ON(.Q(rQ), .S(rS), .R(rR)); 
    always @(startn, stopn,clearn,door_closed,timer_done) begin
        if(!startn  && door_closed)
        begin
            rS= 1; 
            rR = 0; 
            mag_on = rQ; 
        end
        else if(!stopn || timer_done || !door_closed )
        begin
            rS = 0 ; 
            rR = 1 ; 
            mag_on = rQ ; 
        end
        else 
        begin
            rS= 0 ;
            rR = 0 ; 
            mag_on = rQ; 
        end
    end
    always @(startn, door_closed, timer_done) begin
        
    end

endmodule

hdl/control/control_tb.v
`timescale 1ns/1ps
module control_tb();

    //startn , stopn , clearn, door_closed, timer_done, 
	reg startn_TB, stopn_TB, clearn_TB , doorClosed_TB, timerDone_TB;
	wire magOn_TB;

	control DUT(
        .startn(startn_TB), .stopn(stopn_TB), .clearn(clearn_TB),
        .door_closed(doorClosed_TB) , .timer_done(timerDone_TB),
        .mag_on(magOn_TB)  
    );
	initial
		begin
		
			$dumpfile("control_tb.vcd");
			$dumpvars(0,control_tb);

			    startn_TB=0; stopn_TB=0; clearn_TB=0; timerDone_TB=0; doorClosed_TB=0;   
			#10 startn_TB=1; stopn_TB=0; clearn_TB=0; timerDone_TB=0; doorClosed_TB=1; 
			#10 startn_TB=0; stopn_TB=0; clearn_TB=0; timerDone_TB=1; doorClosed_TB=1; 
			#10 startn_TB=0; stopn_TB=1; clearn_TB=0; timerDone_TB=0; doorClosed_TB=1; 
			#10 startn_TB=0; stopn_TB=0; clearn_TB=0; timerDone_TB=0; doorClosed_TB=0; 
			#10 startn_TB=0; stopn_TB=1; clearn_TB=0; timerDone_TB=0; doorClosed_TB=1; 
			#10 startn_TB=0; stopn_TB=0; clearn_TB=1; timerDone_TB=1; doorClosed_TB=0;
            #10 startn_TB=0; stopn_TB=0; clearn_TB=1; timerDone_TB=1; doorClosed_TB=0; 
			#10 startn_TB=0; stopn_TB=1; clearn_TB=1; timerDone_TB=0; doorClosed_TB=0; 
			#10 startn_TB=0; stopn_TB=1; clearn_TB=1; timerDone_TB=0; doorClosed_TB=0; 
			#10 startn_TB=1; stopn_TB=0; clearn_TB=0; timerDone_TB=1; doorClosed_TB=1; 
			#10 startn_TB=1; stopn_TB=0; clearn_TB=0; timerDone_TB=1; doorClosed_TB=1; 
			#10 startn_TB=0; stopn_TB=0; clearn_TB=1; timerDone_TB=1; doorClosed_TB=0; 

		end

endmodule

hdl/control/control_tb.vcd
$date
	Sun Apr 25 22:13:08 2021
$end
$version
	Icarus Verilog
$end
$timescale
	1ps
$end
$scope module control_tb $end
$var wire 1 ! magOn_TB $end
$var reg 1 " clearn_TB $end
$var reg 1 # doorClosed_TB $end
$var reg 1 $ startn_TB $end
$var reg 1 % stopn_TB $end
$var reg 1 & timerDone_TB $end
$scope module DUT $end
$var wire 1 " clearn $end
$var wire 1 # door_closed $end
$var wire 1 $ startn $end
$var wire 1 % stopn $end
$var wire 1 & timer_done $end
$var wire 1 ' rQ $end
$var reg 1 ! mag_on $end
$var reg 1 ( rR $end
$var reg 1 ) rS $end
$scope module LSR_ON $end
$var wire 1 ' Q $end
$var wire 1 ( R $end
$var wire 1 ) S $end
$var reg 1 * rQ $end
$var reg 1 + rQn $end
$upscope $end
$upscope $end
$upscope $end
$scope module latchsr_tb $end
$var wire 1 , Q_TB $end
$var reg 1 - R_TB $end
$var reg 1 . S_TB $end
$scope module DUT $end
$var wire 1 , Q $end
$var wire 1 - R $end
$var wire 1 . S $end
$var reg 1 / rQ $end
$var reg 1 0 rQn $end
$upscope $end
$upscope $end
$enddefinitions $end
#0
$dumpvars
10
1/
0.
0-
1,
1+
0*
0)
1(
0'
0&
0%
0$
0#
0"
1!
$end
#10000
0!
1#
1$
#20000
0+
1'
1*
0,
0/
0(
1)
1-
1&
0$
#30000
1!
0&
1%
#40000
1+
00
1,
1/
1(
0)
0-
1.
0#
0%
#50000
0+
0(
1)
1#
1%
#60000
1+
10
1(
0)
0.
0#
1&
1"
0%
#80000
0&
1%
#100000
1#
1&
0"
0%
1$
#120000
0#
1"
0$
